{"AuxAudioDevice1":{"balance":0.5,"deinterlace_field_order":0,"deinterlace_mode":0,"enabled":true,"flags":0,"hotkeys":{"libobs.mute":[],"libobs.push-to-mute":[],"libobs.push-to-talk":[],"libobs.unmute":[]},"id":"pulse_input_capture","mixers":255,"monitoring_type":0,"muted":true,"name":"Microfono/disp. ausiliario","prev_ver":452984832,"private_settings":{},"push-to-mute":false,"push-to-mute-delay":0,"push-to-talk":false,"push-to-talk-delay":0,"settings":{"device_id":"default"},"sync":0,"versioned_id":"pulse_input_capture","volume":0.97453588247299194},"DesktopAudioDevice1":{"balance":0.5,"deinterlace_field_order":0,"deinterlace_mode":0,"enabled":true,"flags":0,"hotkeys":{"libobs.mute":[],"libobs.push-to-mute":[],"libobs.push-to-talk":[],"libobs.unmute":[]},"id":"pulse_output_capture","mixers":255,"monitoring_type":0,"muted":true,"name":"Audio del desktop","prev_ver":452984832,"private_settings":{},"push-to-mute":false,"push-to-mute-delay":0,"push-to-talk":false,"push-to-talk-delay":0,"settings":{"device_id":"default"},"sync":0,"versioned_id":"pulse_output_capture","volume":1.0},"current_program_scene":"HMI","current_scene":"HMI","current_transition":"Dissolvenza","groups":[],"modules":{"auto-scene-switcher":{"active":false,"interval":300,"non_matching_scene":"","switch_if_not_matching":false,"switches":[]},"decklink_captions":{"source":""},"output-timer":{"autoStartRecordTimer":false,"autoStartStreamTimer":false,"pauseRecordTimer":true,"recordTimerHours":0,"recordTimerMinutes":0,"recordTimerSeconds":30,"streamTimerHours":0,"streamTimerMinutes":0,"streamTimerSeconds":30},"scripts-tool":[]},"name":"scena_server","preview_locked":false,"quick_transitions":[{"duration":300,"fade_to_black":false,"hotkeys":[],"id":1,"name":"Taglio"},{"duration":300,"fade_to_black":false,"hotkeys":[],"id":2,"name":"Dissolvenza"},{"duration":300,"fade_to_black":true,"hotkeys":[],"id":3,"name":"Dissolvenza"}],"saved_projectors":[],"scaling_enabled":false,"scaling_level":0,"scaling_off_x":0.0,"scaling_off_y":0.0,"scene_order":[{"name":"HMI"}],"sources":[{"balance":0.5,"deinterlace_field_order":0,"deinterlace_mode":0,"enabled":true,"flags":0,"hotkeys":{},"id":"text_ft2_source","mixers":0,"monitoring_type":0,"muted":false,"name":"T1_txt 3","prev_ver":452984832,"private_settings":{},"push-to-mute":false,"push-to-mute-delay":0,"push-to-talk":false,"push-to-talk-delay":0,"settings":{"text":"TANK 3"},"sync":0,"versioned_id":"text_ft2_source_v2","volume":1.0},{"balance":0.5,"deinterlace_field_order":0,"deinterlace_mode":0,"enabled":true,"flags":0,"hotkeys":{},"id":"text_ft2_source","mixers":0,"monitoring_type":0,"muted":false,"name":"T1_txt 2","prev_ver":452984832,"private_settings":{},"push-to-mute":false,"push-to-mute-delay":0,"push-to-talk":false,"push-to-talk-delay":0,"settings":{"text":"TANK 2"},"sync":0,"versioned_id":"text_ft2_source_v2","volume":1.0},{"balance":0.5,"deinterlace_field_order":0,"deinterlace_mode":0,"enabled":true,"flags":0,"hotkeys":{},"id":"text_ft2_source","mixers":0,"monitoring_type":0,"muted":false,"name":"T1_txt","prev_ver":452984832,"private_settings":{},"push-to-mute":false,"push-to-mute-delay":0,"push-to-talk":false,"push-to-talk-delay":0,"settings":{"text":"TANK 1"},"sync":0,"versioned_id":"text_ft2_source_v2","volume":1.0},{"balance":0.5,"deinterlace_field_order":0,"deinterlace_mode":0,"enabled":true,"flags":0,"hotkeys":{},"id":"text_ft2_source","mixers":0,"monitoring_type":0,"muted":false,"name":"Scada_txt","prev_ver":452984832,"private_settings":{},"push-to-mute":false,"push-to-mute-delay":0,"push-to-talk":false,"push-to-talk-delay":0,"settings":{"color1":4278190080,"color2":4278190080,"text":"SCADA HMI"},"sync":0,"versioned_id":"text_ft2_source_v2","volume":1.0},{"balance":0.5,"deinterlace_field_order":0,"deinterlace_mode":0,"enabled":true,"flags":0,"hotkeys":{},"id":"xcomposite_input","mixers":0,"monitoring_type":0,"muted":false,"name":"SCADA","prev_ver":452984832,"private_settings":{},"push-to-mute":false,"push-to-mute-delay":0,"push-to-talk":false,"push-to-talk-delay":0,"settings":{"capture_window":"33567762\r\nScadaBR - 1.0 CE – Mozilla Firefox\r\nNavigator","cut_bot":380,"cut_left":14,"cut_right":1200,"cut_top":220},"sync":0,"versioned_id":"xcomposite_input","volume":1.0},{"balance":0.5,"deinterlace_field_order":0,"deinterlace_mode":0,"enabled":true,"flags":0,"hotkeys":{},"id":"xcomposite_input","mixers":0,"monitoring_type":0,"muted":false,"name":"TANK3","prev_ver":452984832,"private_settings":{},"push-to-mute":false,"push-to-mute-delay":0,"push-to-talk":false,"push-to-talk-delay":0,"settings":{"capture_window":"104858581\r\nTank3\r\nsun-awt-X11-XFramePeer","cut_bot":28,"cut_right":0,"cut_top":57},"sync":0,"versioned_id":"xcomposite_input","volume":1.0},{"balance":0.5,"deinterlace_field_order":0,"deinterlace_mode":0,"enabled":true,"flags":0,"hotkeys":{},"id":"xcomposite_input","mixers":0,"monitoring_type":0,"muted":false,"name":"TANK2","prev_ver":452984832,"private_settings":{},"push-to-mute":false,"push-to-mute-delay":0,"push-to-talk":false,"push-to-talk-delay":0,"settings":{"capture_window":"104858572\r\nTank2\r\nsun-awt-X11-XFramePeer","cut_bot":28,"cut_right":5,"cut_top":56},"sync":0,"versioned_id":"xcomposite_input","volume":1.0},{"balance":0.5,"deinterlace_field_order":0,"deinterlace_mode":0,"enabled":true,"flags":0,"hotkeys":{},"id":"xcomposite_input","mixers":0,"monitoring_type":0,"muted":false,"name":"TANK1","prev_ver":452984832,"private_settings":{},"push-to-mute":false,"push-to-mute-delay":0,"push-to-talk":false,"push-to-talk-delay":0,"settings":{"capture_window":"104858558\r\nTank1\r\nsun-awt-X11-XFramePeer","cut_bot":28,"cut_left":2,"cut_top":57},"sync":0,"versioned_id":"xcomposite_input","volume":1.0},{"balance":0.5,"deinterlace_field_order":0,"deinterlace_mode":0,"enabled":true,"flags":0,"hotkeys":{"OBSBasic.SelectScene":[],"libobs.hide_scene_item.SCADA":[],"libobs.hide_scene_item.Scada_txt":[],"libobs.hide_scene_item.T1_txt":[],"libobs.hide_scene_item.T1_txt 2":[],"libobs.hide_scene_item.T1_txt 3":[],"libobs.hide_scene_item.TANK1":[],"libobs.hide_scene_item.TANK2":[],"libobs.hide_scene_item.TANK3":[],"libobs.show_scene_item.SCADA":[],"libobs.show_scene_item.Scada_txt":[],"libobs.show_scene_item.T1_txt":[],"libobs.show_scene_item.T1_txt 2":[],"libobs.show_scene_item.T1_txt 3":[],"libobs.show_scene_item.TANK1":[],"libobs.show_scene_item.TANK2":[],"libobs.show_scene_item.TANK3":[]},"id":"scene","mixers":0,"monitoring_type":0,"muted":false,"name":"HMI","prev_ver":452984832,"private_settings":{},"push-to-mute":false,"push-to-mute-delay":0,"push-to-talk":false,"push-to-talk-delay":0,"settings":{"custom_size":false,"id_counter":11,"items":[{"align":5,"bounds":{"x":0.0,"y":0.0},"bounds_align":0,"bounds_type":0,"crop_bottom":0,"crop_left":0,"crop_right":0,"crop_top":0,"group_item_backup":false,"hide_transition":{"duration":0},"id":2,"locked":false,"name":"TANK1","pos":{"x":1412.0,"y":0.0},"private_settings":{},"rot":0.0,"scale":{"x":0.93211007118225098,"y":0.93300247192382812},"scale_filter":"disable","show_transition":{"duration":0},"visible":true},{"align":5,"bounds":{"x":0.0,"y":0.0},"bounds_align":0,"bounds_type":0,"crop_bottom":0,"crop_left":0,"crop_right":0,"crop_top":0,"group_item_backup":false,"hide_transition":{"duration":0},"id":3,"locked":false,"name":"TANK2","pos":{"x":1407.0,"y":377.0},"private_settings":{},"rot":0.0,"scale":{"x":0.946494460105896,"y":0.9455445408821106},"scale_filter":"disable","show_transition":{"duration":0},"visible":true},{"align":5,"bounds":{"x":0.0,"y":0.0},"bounds_align":0,"bounds_type":0,"crop_bottom":0,"crop_left":0,"crop_right":0,"crop_top":0,"group_item_backup":false,"hide_transition":{"duration":0},"id":4,"locked":false,"name":"TANK3","pos":{"x":1407.0,"y":759.0},"private_settings":{},"rot":0.0,"scale":{"x":0.86949151754379272,"y":0.86991870403289795},"scale_filter":"disable","show_transition":{"duration":0},"visible":true},{"align":5,"bounds":{"x":0.0,"y":0.0},"bounds_align":0,"bounds_type":0,"crop_bottom":0,"crop_left":0,"crop_right":0,"crop_top":0,"group_item_backup":false,"hide_transition":{"duration":0},"id":6,"locked":false,"name":"SCADA","pos":{"x":36.0,"y":51.0},"private_settings":{},"rot":0.0,"scale":{"x":2.1230282783508301,"y":2.1236202716827393},"scale_filter":"disable","show_transition":{"duration":0},"visible":true},{"align":5,"bounds":{"x":0.0,"y":0.0},"bounds_align":0,"bounds_type":0,"crop_bottom":0,"crop_left":0,"crop_right":0,"crop_top":0,"group_item_backup":false,"hide_transition":{"duration":0},"id":7,"locked":false,"name":"Scada_txt","pos":{"x":821.0,"y":59.0},"private_settings":{},"rot":0.0,"scale":{"x":0.18219177424907684,"y":0.18076923489570618},"scale_filter":"disable","show_transition":{"duration":0},"visible":true},{"align":5,"bounds":{"x":0.0,"y":0.0},"bounds_align":0,"bounds_type":0,"crop_bottom":0,"crop_left":0,"crop_right":0,"crop_top":0,"group_item_backup":false,"hide_transition":{"duration":0},"id":8,"locked":false,"name":"T1_txt","pos":{"x":1440.0,"y":304.0},"private_settings":{},"rot":0.0,"scale":{"x":0.14438502490520477,"y":0.14453125},"scale_filter":"disable","show_transition":{"duration":0},"visible":true},{"align":5,"bounds":{"x":0.0,"y":0.0},"bounds_align":0,"bounds_type":0,"crop_bottom":0,"crop_left":0,"crop_right":0,"crop_top":0,"group_item_backup":false,"hide_transition":{"duration":0},"id":9,"locked":false,"name":"T1_txt 2","pos":{"x":1435.0,"y":694.0},"private_settings":{},"rot":0.0,"scale":{"x":0.14438502490520477,"y":0.14453125},"scale_filter":"disable","show_transition":{"duration":0},"visible":true},{"align":5,"bounds":{"x":0.0,"y":0.0},"bounds_align":0,"bounds_type":0,"crop_bottom":0,"crop_left":0,"crop_right":0,"crop_top":0,"group_item_backup":false,"hide_transition":{"duration":0},"id":10,"locked":false,"name":"T1_txt 3","pos":{"x":1443.0,"y":1007.0},"private_settings":{},"rot":0.0,"scale":{"x":0.14438502490520477,"y":0.14453125},"scale_filter":"disable","show_transition":{"duration":0},"visible":true}]},"sync":0,"versioned_id":"scene","volume":1.0}],"transition_duration":300,"transitions":[]}